{
 "_doc": "VVV factory preset knob values read from plugin-GUI screenshots (2026-06-16). DISPLAY values exactly as shown. Converted to host-norms via vvv_calib (display->norm) for headless render. param label map: BassFreq=BassXover, Early=EarlyDiffusion, Late=LateDiffusion, Rate=ModRate, Depth=ModDepth, MODE=ReverbMode, COLOR=ColorMode.",
 "reverbmode_norm": {
  "Concert Hall": 0.02,
  "Plate": 0.1,
  "Room": 0.15,
  "Chamber": 0.2,
  "Chorus Space": 0.25,
  "Ambience": 0.3,
  "Bright Hall": 0.35,
  "Sanctuary": 0.4,
  "Cathedral": 0.8,
  "Chamber1979": 0.9,
  "Hall1984": 0.95
 },
 "colormode_norm": {
  "1970s": 0.2,
  "1980s": 0.78,
  "NOW": 1.0
 },
 "presets": {
  "vvv-drum-plate": {
   "PRESET": "Drum Plate",
   "MODE": "Plate",
   "COLOR": "NOW",
   "Mix_pct": 100.0,
   "PreDelay_ms": 0.0,
   "Decay_s": 1.2,
   "HighFreq_Hz": 20000,
   "HighShelf_dB": 0.0,
   "BassFreq_Hz": 5280,
   "BassMult_X": 1.5,
   "Size_pct": 80.0,
   "Attack_pct": 0.0,
   "Early_pct": 100.0,
   "Late_pct": 100.0,
   "Rate_Hz": 1.2,
   "Depth_pct": 19.2,
   "HighCut_Hz": 4800,
   "LowCut_Hz": 10
  },
  "vvv-bright-hall": {
   "PRESET": "Bright Hall",
   "MODE": "Bright Hall",
   "COLOR": "1980s",
   "Mix_pct": 100.0,
   "PreDelay_ms": 20.0,
   "Decay_s": 4.0,
   "HighFreq_Hz": 6000,
   "HighShelf_dB": -24.0,
   "BassFreq_Hz": 470,
   "BassMult_X": 1.5,
   "Size_pct": 100.0,
   "Attack_pct": 50.0,
   "Early_pct": 100.0,
   "Late_pct": 100.0,
   "Rate_Hz": 2.53,
   "Depth_pct": 31.6,
   "HighCut_Hz": 8000,
   "LowCut_Hz": 10
  },
  "vvv-vocal-hall": {
   "PRESET": "Vocal Hall",
   "MODE": "Concert Hall",
   "COLOR": "NOW",
   "Mix_pct": 100.0,
   "PreDelay_ms": 8.0,
   "Decay_s": 2.17,
   "HighFreq_Hz": 6000,
   "HighShelf_dB": -10.0,
   "BassFreq_Hz": 700,
   "BassMult_X": 2.0,
   "Size_pct": 100.0,
   "Attack_pct": 10.0,
   "Early_pct": 100.0,
   "Late_pct": 100.0,
   "Rate_Hz": 2.25,
   "Depth_pct": 23.0,
   "HighCut_Hz": 7000,
   "LowCut_Hz": 50
  },
  "vvv-cathedral": {
   "PRESET": "CathedralLargeHall",
   "MODE": "Cathedral",
   "COLOR": "NOW",
   "Mix_pct": 100.0,
   "PreDelay_ms": 20.0,
   "Decay_s": 2.7,
   "HighFreq_Hz": 2200,
   "HighShelf_dB": -12.0,
   "BassFreq_Hz": 270,
   "BassMult_X": 1.3,
   "Size_pct": 80.0,
   "Attack_pct": 50.0,
   "Early_pct": 100.0,
   "Late_pct": 100.0,
   "Rate_Hz": 0.25,
   "Depth_pct": 75.0,
   "HighCut_Hz": 4000,
   "LowCut_Hz": 10,
   "_attack_confirm": "Attack readback low-confidence from screenshot"
  },
  "vvv-79vc": {
   "PRESET": "79 Vocal Chamber",
   "MODE": "Chamber1979",
   "COLOR": "1970s",
   "Mix_pct": 100.0,
   "PreDelay_ms": 0.0,
   "Decay_s": 3.0,
   "HighFreq_Hz": 6000,
   "HighShelf_dB": -24.0,
   "BassFreq_Hz": 300,
   "BassMult_X": 1.5,
   "Size_pct": 100.0,
   "Attack_pct": 0.0,
   "Early_pct": 100.0,
   "Late_pct": 100.0,
   "Rate_Hz": 0.54,
   "Depth_pct": 50.0,
   "HighCut_Hz": 20000,
   "LowCut_Hz": 10
  },
  "vvv-tiled-room": {
   "PRESET": "Tiled Room",
   "MODE": "Chamber",
   "COLOR": "1980s",
   "Mix_pct": 100.0,
   "PreDelay_ms": 4.0,
   "Decay_s": 0.62,
   "HighFreq_Hz": 9020,
   "HighShelf_dB": -24.0,
   "BassFreq_Hz": 2850,
   "BassMult_X": 1.25,
   "Size_pct": 10.7,
   "Attack_pct": 0.0,
   "Early_pct": 35.0,
   "Late_pct": 50.0,
   "Rate_Hz": 0.78,
   "Depth_pct": 14.4,
   "HighCut_Hz": 10000,
   "LowCut_Hz": 10
  },
  "vvv-ambience": {
   "PRESET": "Ambience",
   "MODE": "Ambience",
   "COLOR": "1980s",
   "Mix_pct": 100.0,
   "PreDelay_ms": 0.0,
   "Decay_s": 0.8,
   "HighFreq_Hz": 10000,
   "HighShelf_dB": -24.0,
   "BassFreq_Hz": 160,
   "BassMult_X": 2.0,
   "Size_pct": 20.0,
   "Attack_pct": 35.6,
   "Early_pct": 100.0,
   "Late_pct": 100.0,
   "Rate_Hz": 0.32,
   "Depth_pct": 36.0,
   "HighCut_Hz": 15000,
   "LowCut_Hz": 10
  },
  "vvv-blade-runner": {
   "PRESET": "Homestar Blade Runner",
   "MODE": "Concert Hall",
   "COLOR": "1980s",
   "Mix_pct": 100.0,
   "PreDelay_ms": 31.0,
   "Decay_s": 10.0,
   "HighFreq_Hz": 4890,
   "HighShelf_dB": -24.0,
   "BassFreq_Hz": 530,
   "BassMult_X": 1.5,
   "Size_pct": 100.0,
   "Attack_pct": 48.4,
   "Early_pct": 43.8,
   "Late_pct": 70.0,
   "Rate_Hz": 3.99,
   "Depth_pct": 35.6,
   "HighCut_Hz": 6000,
   "LowCut_Hz": 10
  },
  "vvv-84-small-room": {
   "PRESET": "84 Small Room",
   "MODE": "Hall1984",
   "COLOR": "1980s",
   "Mix_pct": 100.0,
   "PreDelay_ms": 0.0,
   "Decay_s": 0.5,
   "HighFreq_Hz": 4400,
   "HighShelf_dB": -24.0,
   "BassFreq_Hz": 700,
   "BassMult_X": 0.5,
   "Size_pct": 0.0,
   "Attack_pct": 0.0,
   "Early_pct": 50.0,
   "Late_pct": 100.0,
   "Rate_Hz": 1.21,
   "Depth_pct": 25.0,
   "HighCut_Hz": 4400,
   "LowCut_Hz": 10
  },
  "vvv-fat-snare-room": {
   "PRESET": "Fat Snare Room",
   "MODE": "Room",
   "COLOR": "1980s",
   "Mix_pct": 100.0,
   "PreDelay_ms": 9.0,
   "Decay_s": 0.7,
   "HighFreq_Hz": 6600,
   "HighShelf_dB": -24.0,
   "BassFreq_Hz": 630,
   "BassMult_X": 1.25,
   "Size_pct": 38.8,
   "Attack_pct": 12.4,
   "Early_pct": 68.0,
   "Late_pct": 100.0,
   "Rate_Hz": 1.5,
   "Depth_pct": 30.8,
   "HighCut_Hz": 4500,
   "LowCut_Hz": 10
  },
  "vvv-vocal-plate": {
   "PRESET": "Vocal Plate",
   "MODE": "Plate",
   "COLOR": "NOW",
   "Mix_pct": 100.0,
   "PreDelay_ms": 20.0,
   "Decay_s": 0.71,
   "HighFreq_Hz": 5500,
   "HighShelf_dB": -12.0,
   "BassFreq_Hz": 7560,
   "BassMult_X": 1.0,
   "Size_pct": 44.0,
   "Attack_pct": 20.0,
   "Early_pct": 18.8,
   "Late_pct": 100.0,
   "Rate_Hz": 1.8,
   "Depth_pct": 19.2,
   "HighCut_Hz": 20000,
   "LowCut_Hz": 10
  }
 }
}